Metadata-Version: 2.1
Name: topsis-102203128
Version: 1.0.1
Summary: A Python package to calculate TOPSIS scores
Home-page: https://github.com/rishikam23/Topsis-Rishika-102203128
Author: Rishika Mathur
Author-email: rmathur_be22@thapar.edu
License-File: LICENSE
Requires-Dist: pandas
Requires-Dist: numpy
